{
  "_declaration": {
    "_attributes": {
      "version": "1.0",
      "encoding": "utf-8"
    }
  },
  "rss": {
    "_attributes": {
      "version": "2.0"
    },
    "channel": {
      "title": {
        "_text": "巴哈姆特 GNN 新聞網"
      },
      "link": {
        "_text": "https://gnn.gamer.com.tw/"
      },
      "description": {
        "_text": "巴哈姆特 GNN 新聞網"
      },
      "language": {
        "_text": "zh-tw"
      },
      "lastBuildDate": {
        "_text": "Thu, 03 Jul 2025 06:37:09 +0800"
      },
      "image": {
        "title": {
          "_text": "巴哈姆特 GNN 新聞網"
        },
        "width": {
          "_text": "154"
        },
        "height": {
          "_text": "99"
        },
        "link": {
          "_text": "https://www.gamer.com.tw/"
        },
        "url": {
          "_text": "https://i2.bahamut.com.tw/bahamut.gif"
        }
      },
      "item": [
        {
          "title": {
            "_cdata": "《數碼寶貝物語 時空異客》製作人帶來長約 10 分鐘的深入解析影片"
          },
          "description": {
            "_cdata": "\n\n　　萬代南夢宮娛樂（Bandai Namco Entertainment）於今日清晨舉辦的線上發表會「Bandai Namco Summer Showcase 2025」中公布了《數碼寶貝物語 時空異客》最新影片，由製作人原良輔深入解析遊戲內容。本作是《數碼寶貝物語》系列睽違十年的全新作品。在正式介紹遊戲內容之前，...."
          },
          "link": {
            "_cdata": "https://gnn.gamer.com.tw/detail.php?sn=288213"
          },
          "pubDate": {
            "_text": "Thu, 03 Jul 2025 06:37:08 +0800"
          }
        },
        {
          "title": {
            "_cdata": "《七龍珠 Z 卡卡洛特》公開最新 DLC「-DAIMA- 魔界大冒險！PART1」實機遊玩介紹影片"
          },
          "description": {
            "_cdata": "\n　　萬代南夢宮娛樂在今日凌晨播出的線上節目「Bandai Namco Summer Showcase」中，公開了動作 RPG《七龍珠 Z 卡卡洛特》（PS5 / PS4 / Switch / Xbox Series X|S / Xbox One / Steam）即將於 7 月 17 日釋出之最新付費下載內容「-DAI...."
          },
          "link": {
            "_cdata": "https://gnn.gamer.com.tw/detail.php?sn=288212"
          },
          "pubDate": {
            "_text": "Thu, 03 Jul 2025 05:07:13 +0800"
          }
        },
        {
          "title": {
            "_cdata": "《死亡筆記本 暗影任務》公布最新宣傳影片 預計夏季實裝更多新角色"
          },
          "description": {
            "_cdata": "\n　　萬代南夢宮娛樂（Bandai Namco Entertainment）於今日清晨舉辦的線上發表會「Bandai Namco Summer Showcase 2025」中，公布了改編自人氣 IP《死亡筆記本》之家用主機遊戲《死亡筆記本 暗影任務》的最新宣傳影片。\n\n&nbsp;\n\n\n\n\n\n\n\n&nbsp;\n\n\n\n\n...."
          },
          "link": {
            "_cdata": "https://gnn.gamer.com.tw/detail.php?sn=288211"
          },
          "pubDate": {
            "_text": "Thu, 03 Jul 2025 04:50:32 +0800"
          }
        },
        {
          "title": {
            "_cdata": "Rougelite RPG 新作《永久與神樹的祈願者》公開最新宣傳影片 一窺祈願者活躍的場面"
          },
          "description": {
            "_cdata": "\n　　Brownies inc. 開發、萬代南夢宮娛樂預定 9 月 18、19 日推出的角色扮演遊戲《永久與神樹的祈願者》（PS5 / Nintendo Switch / Xbox Series X|S / Steam），在今日凌晨播出的線上節目「Bandai Namco Summer Showcase」公開了最新宣傳...."
          },
          "link": {
            "_cdata": "https://gnn.gamer.com.tw/detail.php?sn=288210"
          },
          "pubDate": {
            "_text": "Thu, 03 Jul 2025 04:13:56 +0800"
          }
        },
        {
          "title": {
            "_cdata": "《我的英雄學院 無盡正義》正式發表！以最終決戰為主題的對戰動作最新作"
          },
          "description": {
            "_cdata": "\n\n　　萬代南夢宮娛樂（Bandai Namco Entertainment）於今日清晨舉辦的線上發表會「Bandai Namco Summer Showcase 2025」中，正式公開了改編自《我的英雄學院》的最新家用遊戲作品《我的英雄學院 無盡正義（僕のヒーローアカデミア All&#39;s Justice）》（P...."
          },
          "link": {
            "_cdata": "https://gnn.gamer.com.tw/detail.php?sn=288209"
          },
          "pubDate": {
            "_text": "Thu, 03 Jul 2025 03:46:56 +0800"
          }
        },
        {
          "title": {
            "_cdata": "《絕地求生 PUBG》預告將與韓國人氣女團「aespa」推出合作內容"
          },
          "description": {
            "_cdata": "\n\n　　KRAFTON 今日預告，旗下遊戲《絕地求生（PUBG)》與韓國 SM 娛樂旗下的人氣 K-pop 女團「aespa」合作內容即將於 7 月 9 日在 PC 平台登場。\n\n&nbsp;\n\n　　KRAFTON 尚未揭露雙方合作的內容，僅表示「aespa」將帶著「big flash」降落戰場，誰將是統治這個虛擬戰場...."
          },
          "link": {
            "_cdata": "https://gnn.gamer.com.tw/detail.php?sn=288208"
          },
          "pubDate": {
            "_text": "Wed, 02 Jul 2025 19:48:00 +0800"
          }
        },
        {
          "title": {
            "_cdata": "《第一繼承者》宣布 8 月 7 日推出與《尼爾：自動人形》合作內容"
          },
          "description": {
            "_cdata": "\n\n　　NEXON GAMES 今（2）日舉辦「Descendant Fest 2025」線上發表會，以慶祝旗下團隊射擊動作角色扮演遊戲《第一繼承者（The First Descendant）》一週年，正式揭曉將與 SQUARE ENIX《尼爾：自動人形》合作宣傳影片，預定 8 月 7 日正式推出。\n\n&nbsp;\n\n...."
          },
          "link": {
            "_cdata": "https://gnn.gamer.com.tw/detail.php?sn=288207"
          },
          "pubDate": {
            "_text": "Wed, 02 Jul 2025 19:35:08 +0800"
          }
        },
        {
          "title": {
            "_cdata": "銷量或預測？外媒報導任天堂官網意外刊出 Switch 2 首月全球販售數量"
          },
          "description": {
            "_cdata": "\n\n　　根據外媒報導，任天堂 IR 官網曾一度公開 Nintendo Switch 2 地區銷售數據圖表（※ 已從官網撤下，但網路上仍有保留截圖），寫到最新家用主機 Nintendo Switch 2 在上市首月（2025 年 6 月）全球銷量突破 500 萬台，美洲地區約售出 180 萬台，其次為日本 147 萬台、...."
          },
          "link": {
            "_cdata": "https://gnn.gamer.com.tw/detail.php?sn=288206"
          },
          "pubDate": {
            "_text": "Wed, 02 Jul 2025 19:28:58 +0800"
          }
        },
        {
          "title": {
            "_cdata": "NVIDIA 宣布《Mecha BREAK》、《暗黑破壞神 4》等遊戲支援具有多畫格生成的 DLSS 4"
          },
          "description": {
            "_cdata": "\n　　NVIDIA 今日宣布，具有多畫格生成的 DLSS 4 將為《Mecha BREAK》帶來效能提升，同時《暗黑破壞神 4》與《覺醒深淵（Still Wakes the Deep）》也透過全更新內容加入原生支援，讓 GeForce RTX 50 系列玩家能夠享受到更好的遊戲效能。此外，《異環（Neverness t...."
          },
          "link": {
            "_cdata": "https://gnn.gamer.com.tw/detail.php?sn=288205"
          },
          "pubDate": {
            "_text": "Wed, 02 Jul 2025 19:00:12 +0800"
          }
        },
        {
          "title": {
            "_cdata": "Acer  27 吋薄型 2K 螢幕 SH272U G0  上市"
          },
          "description": {
            "_cdata": "\n\n　　宏碁宣布推出全新薄型螢幕 Acer SH272U G0。這款 27 吋 2K 螢幕具有約 7.2mm 的薄型機身與 ZeroFrame 極窄邊框設計，並擁有 120Hz 的流暢刷新率，以及可升降旋轉的人體工學設計，希望確保使用者長時間使用也能擁有良好的視覺與身體舒適度。\n\n&nbsp;\n\n\n\n\n\n\n\n&nbsp...."
          },
          "link": {
            "_cdata": "https://gnn.gamer.com.tw/detail.php?sn=288204"
          },
          "pubDate": {
            "_text": "Wed, 02 Jul 2025 18:51:29 +0800"
          }
        },
        {
          "title": {
            "_cdata": "動漫周邊概念店「FURU1 × 漫畫展」將於 7/12 在西門町開幕"
          },
          "description": {
            "_cdata": "\n\n　　由結合販售漫畫與動畫周邊商品的「漫畫展」，與主打動漫娛樂與公仔商品的「FURU1（ふるいち）」合作的嶄新概念店「FURU1 &times; 漫畫展」宣布首次登陸台灣，確定進軍台北西門町。包括《鬼滅之刃》、《藍色監獄》、《鏈鋸人》、《咒術迴戰》、《JoJo 的奇妙冒險》等多款熱門動畫限定周邊商品都將上市，預計將於...."
          },
          "link": {
            "_cdata": "https://gnn.gamer.com.tw/detail.php?sn=288203"
          },
          "pubDate": {
            "_text": "Wed, 02 Jul 2025 18:20:12 +0800"
          }
        },
        {
          "title": {
            "_cdata": "《Garena Free Fire》8 周年攜手高雄捷運跨界合作 貓咪站長「蜜柑」領航經典夥伴回歸"
          },
          "description": {
            "_cdata": "\n\n\n　　《Garena Free Fire》已陪伴玩家走過八個年頭，為慶祝這個充滿意義的時刻，《Free Fire 8 周年：時光列車》本次以「8 = &infin;」為主題，象徵回憶不滅、夥伴常在、未來無限等意義，而除了遊戲內活動外，更首度攜手高雄捷運與貓咪站長「蜜柑」推出一系列跨界合作，並邀請歷屆經典夥伴齊聚 M...."
          },
          "link": {
            "_cdata": "https://gnn.gamer.com.tw/detail.php?sn=288202"
          },
          "pubDate": {
            "_text": "Wed, 02 Jul 2025 18:15:04 +0800"
          }
        },
        {
          "title": {
            "_cdata": "《幻想神域：源神啟動》全球版正式上市 與台灣人氣 IP「白爛貓」展開聯動合作"
          },
          "description": {
            "_cdata": "\n　　由傳奇網路遊戲所研發的大型線上奇幻風格 MMORPG 遊戲《幻想神域：源神啟動》於今（2）日正式開服，啟源使者們將再次踏上這片充滿幻想與冒險的大地，與形影不離的「源神」夥伴們共同創造嶄新的傳奇篇章。官方表示，為慶祝遊戲盛大上市，營運團隊宣布與台灣人氣 IP「白爛貓」展開跨界聯動合作，一系列趣味活動同步開跑。\n\n\n...."
          },
          "link": {
            "_cdata": "https://gnn.gamer.com.tw/detail.php?sn=288201"
          },
          "pubDate": {
            "_text": "Wed, 02 Jul 2025 18:11:54 +0800"
          }
        },
        {
          "title": {
            "_cdata": "華碩推出全新 TUF Gaming 系列 5 電競螢幕 具備多樣化規格"
          },
          "description": {
            "_cdata": "\n\n　　華碩宣布推出全新 TUF Gaming 系列 5 電競螢幕，尺寸涵蓋 23.8 吋至 34 吋，且具備 FHD、QHD 或 WQHD 面板等多樣化規格，將全力滿足不同玩家族群需求。\n\n&nbsp;\n\n\n\n\n\n\n\n&nbsp;\n\n\n【以下內容為廠商提供資料原文】\n\n\n&nbsp;\n\n　　而為打造無懈可擊的「五星級...."
          },
          "link": {
            "_cdata": "https://gnn.gamer.com.tw/detail.php?sn=288200"
          },
          "pubDate": {
            "_text": "Wed, 02 Jul 2025 18:06:58 +0800"
          }
        },
        {
          "title": {
            "_cdata": "《魔法門之英雄無敵：上古紀元》預告今年內將於 Steam 展開搶先體驗"
          },
          "description": {
            "_cdata": "\n\n　　Hooded Horse 宣布，已與 Ubisoft 和 Unfrozen 達成協議，將擔任《魔法門之英雄無敵：上古紀元》的發行商，該遊戲計畫今年稍晚透過 Steam 搶先體驗發布。\n\n&nbsp;\n\n\n\n\n\n&nbsp;\n\n　　官方表示，曾製作奇幻戰術 RPG《伊拉圖斯：死之主》的 Unfrozen 工作室將...."
          },
          "link": {
            "_cdata": "https://gnn.gamer.com.tw/detail.php?sn=288199"
          },
          "pubDate": {
            "_text": "Wed, 02 Jul 2025 17:57:08 +0800"
          }
        },
        {
          "title": {
            "_cdata": "《魔物獵人 荒野》針對調查任務異常問題補償公會點數與重鎧玉"
          },
          "description": {
            "_cdata": "\n　　CAPCOM 今日發布關於《魔物獵人 荒野》調查任務的異常問題之致歉與說明，表示已確認在第二彈大型免費更新套用前所儲存的調查任務中，會發生魔物體型異常變動的問題。\n\n&nbsp;\n\n※ 此問題不會發生於更新套用後儲存的調查任務。\n\n&nbsp;\n\n　　官方提到，經過詳細調查與評估後，判斷短期內難以完成修復作業，對...."
          },
          "link": {
            "_cdata": "https://gnn.gamer.com.tw/detail.php?sn=288198"
          },
          "pubDate": {
            "_text": "Wed, 02 Jul 2025 17:55:07 +0800"
          }
        },
        {
          "title": {
            "_cdata": "GRAVITY 揭露全球戰略藍圖 將推進 IP 多元化發展 主打大世界探索《RO 世界》預計 Q4 上市"
          },
          "description": {
            "_cdata": "\n　　GRAVITY 於今（2）日舉辦「GRAVITY 品牌戰略發表會」，由集團董事長北村佳紀親自揭示未來藍圖，正式宣布 GRAVITY 將邁向「全球第一的遊戲娛樂企業」之願景，並以《RO 仙境傳說》為核心，推進 IP 多元化發展。他強調：「我們不再只是開發遊戲，更要打造能夠觸動情感、引發共鳴的互動型娛樂體驗，透過遊戲...."
          },
          "link": {
            "_cdata": "https://gnn.gamer.com.tw/detail.php?sn=288197"
          },
          "pubDate": {
            "_text": "Wed, 02 Jul 2025 17:51:18 +0800"
          }
        },
        {
          "title": {
            "_cdata": "暗黑像素風動作遊戲《血湧不息》搶先體驗版於 Steam 上線 公開宣傳影片與未來更新藍圖"
          },
          "description": {
            "_cdata": "\n\n　　由巴西開發團隊 Lightmancer Studios 製作、Nuntius Games 與 Vsoo Games 聯合發行的暗黑像素風動作遊戲《血湧不息（BloodRush: Undying Wish）》現已在 Steam 推出搶先體驗版本，並同步公開全新宣傳影片及完整開發藍圖，慶祝上市之餘也帶來限時 10%...."
          },
          "link": {
            "_cdata": "https://gnn.gamer.com.tw/detail.php?sn=288196"
          },
          "pubDate": {
            "_text": "Wed, 02 Jul 2025 17:47:49 +0800"
          }
        },
        {
          "title": {
            "_cdata": "《天使之戀 2 Online》全新改版「幽影夜襲」上線 新增全新主城古堡前院與對應故事"
          },
          "description": {
            "_cdata": "\n\n　　《天使之戀 2 Online》於 7/2（三）推出最新改版資料片「幽影夜襲」。官方表示，改版內容除了新增全新主城－古堡前院與對應故事，同步開放等級上限至 285 級、追加全新裝備、進階職業 LV252 技能、聖拳鬥士／魔槍士 LV220～228 進階技能，全新副本、怪物、任務、BOSS 等待勇者們挑戰。此外，通...."
          },
          "link": {
            "_cdata": "https://gnn.gamer.com.tw/detail.php?sn=288195"
          },
          "pubDate": {
            "_text": "Wed, 02 Jul 2025 17:38:24 +0800"
          }
        },
        {
          "title": {
            "_cdata": "《Trove》歡慶十週年 「太陽慶典」活動 2025 盛大開啟"
          },
          "description": {
            "_cdata": "\n\n　　MMORPG 發行商 gamigo 今日宣布，旗下像素網遊《Trove》迎來上線十週年。為慶祝這一重要時刻，遊戲內一年一度的「太陽慶典」活動也同步升級為史上規模最大、持續時間最長的一屆：活動將貫穿整個 7 月，讓玩家整月狂歡不斷。\n\n&nbsp;\n\n\n\n\n\n\n\n&nbsp;\n\n\n【以下內容為廠商提供資料原文】\n...."
          },
          "link": {
            "_cdata": "https://gnn.gamer.com.tw/detail.php?sn=288193"
          },
          "pubDate": {
            "_text": "Wed, 02 Jul 2025 17:35:25 +0800"
          }
        },
        {
          "title": {
            "_cdata": "《永劫無間》四周年慶典「無間鏢客」新玩法公開 小李飛刀登場、尼爾等經典 IP 聯動回歸"
          },
          "description": {
            "_cdata": "\n\n　　由艾肯娛樂代理的 STEAM 動作武俠競技遊戲《永劫無間》迎來四週年里程碑，今（2）日盛大舉辦【四周年沙海發布會】，向全球玩家發布未來版本更新與聯動內容。不僅首度公開全新核心玩法「無間鏢客」武俠摸金模式，更搶先曝光《小李飛刀》、《畫江湖之不良人》、《李小龍》等經典 IP 聯動預告，其中「小李飛刀－李尋歡」將作為...."
          },
          "link": {
            "_cdata": "https://gnn.gamer.com.tw/detail.php?sn=288192"
          },
          "pubDate": {
            "_text": "Wed, 02 Jul 2025 17:30:28 +0800"
          }
        },
        {
          "title": {
            "_cdata": "文字冒險類遊戲《薛丁格的電話》期間限定公開試玩 Demo 釋出新視覺圖與 PV"
          },
          "description": {
            "_cdata": "\n\n　　集英社遊戲本（2）日宣布，由獨立遊戲開發團隊 Acrobatic Chirimenjako 製作的文字冒險遊戲《薛丁格的電話》將在 Steam 上再次期間限定公開試玩 Demo，與其一並公開的還有遊戲的新 KV 和 PV。在新 KV 和 PV 中，都有在目前公開的試玩版中還未登場的本篇角色出現。\n\n&nbsp;...."
          },
          "link": {
            "_cdata": "https://gnn.gamer.com.tw/detail.php?sn=288190"
          },
          "pubDate": {
            "_text": "Wed, 02 Jul 2025 17:15:01 +0800"
          }
        },
        {
          "title": {
            "_cdata": "《Final Fantasy IX》原創繪本「比比與爺爺的啟程之日」今日上市 宣傳影片同步公開"
          },
          "description": {
            "_cdata": "\n　　SQUARE ENIX 今日（7/2）出版了《Final Fantasy IX》的原創繪本「比比與爺爺的啟程之日」。\n\n&nbsp;\n\n\n\n\n\n\n\n&nbsp;\n\n\n　　《Final Fantasy IX》是《Final Fantasy》系列本傳第九代作品，2000 年 7 月 7 日在 PlayStation ...."
          },
          "link": {
            "_cdata": "https://gnn.gamer.com.tw/detail.php?sn=288189"
          },
          "pubDate": {
            "_text": "Wed, 02 Jul 2025 17:13:29 +0800"
          }
        },
        {
          "title": {
            "_cdata": "《黑色沙漠》新職業「悟空」乘雲登場 海地爾宴會公開新地區「艾達尼亞」等更新情報"
          },
          "description": {
            "_cdata": "\n\n　　韓國遊戲研發商珍艾碧絲所研發營運的 MMORPG《黑色沙漠》於今（2）日推出揮舞如意棒、騰雲駕霧的全新職業「悟空」，專屬成長活動同步登場。夏季慶典「海地爾宴會」圓滿落幕，釋出包含全新地區「艾達尼亞」、創世級防具／輔助武器、戰鬥系統改版等重要更新方向，期望為每個冒險階段帶來全新展望。\n\n&nbsp;\n\n\n\n\n\n\n...."
          },
          "link": {
            "_cdata": "https://gnn.gamer.com.tw/detail.php?sn=288188"
          },
          "pubDate": {
            "_text": "Wed, 02 Jul 2025 17:09:34 +0800"
          }
        },
        {
          "title": {
            "_cdata": "《碧藍幻想 Relink》全球累計銷售突破 200 萬套"
          },
          "description": {
            "_cdata": "\n\n　　負責遊戲企劃、開發、營運事業的 Cygames Inc.（以下簡稱 Cygames，總公司位置：東京都澀谷區，常務董事兼執行長：渡邊耕一）宣布，旗下 Steam、PlayStation 5、PlayStation 4 專用動作 RPG《碧藍幻想 Relink》（以下簡稱《Relink》）全球累計銷售量已突破 2...."
          },
          "link": {
            "_cdata": "https://gnn.gamer.com.tw/detail.php?sn=288185"
          },
          "pubDate": {
            "_text": "Wed, 02 Jul 2025 16:53:57 +0800"
          }
        },
        {
          "title": {
            "_cdata": "EA SPORTS「FC 未來」計畫兩年內讓社區足球活動參與人數達 50 萬人"
          },
          "description": {
            "_cdata": "\n\n　　Electronic Arts, Inc.（EA）今日宣布，EA SPORTS「FC 未來」的影響力比去年再加倍，讓草根足球的參與人數於第二年突破 34 萬*。有鑑於第一年的 17 萬**人，這同時也代表著本計畫從開始至今的短短兩年內，讓這款全世界的遊戲遊玩人數突破 50 萬。\n\n&nbsp;\n\n\n\n\n\n\n\n&...."
          },
          "link": {
            "_cdata": "https://gnn.gamer.com.tw/detail.php?sn=288184"
          },
          "pubDate": {
            "_text": "Wed, 02 Jul 2025 16:40:02 +0800"
          }
        },
        {
          "title": {
            "_cdata": "《飆酷車神：動力慶典》第 7 季今日推出 法拉利領銜帶來歐洲汽車工藝盛會"
          },
          "description": {
            "_cdata": "\n\n　　Ubisoft 今日宣布，《飆酷車神：動力慶典》第 7 季更新於所有平台推出，本季旨在向以法拉利為首的歐洲豪華與性能汽車製造商的傳奇工藝致敬。本季將為玩家帶來身歷其境的 Ferrari 體驗、全新載具，並且深入探索汽車歷史。\n\n&nbsp;\n\n\n\n\n\n\n\n&nbsp;\n\n\n\n\n\n《飆酷車神：動力慶典》第 7 季...."
          },
          "link": {
            "_cdata": "https://gnn.gamer.com.tw/detail.php?sn=288183"
          },
          "pubDate": {
            "_text": "Wed, 02 Jul 2025 16:33:07 +0800"
          }
        },
        {
          "title": {
            "_cdata": "《夢王國與沉睡中的 100 位王子殿下》開放全新活動「飛向未來的希望之翼」"
          },
          "description": {
            "_cdata": "\n\n\n　　和信超媒體戲谷分公司代理之戀愛養成手遊《夢王國與沉睡中的 100 位王子殿下》（以下簡稱《夢 100》）繁中版今日宣布全新活動「飛向未來的希望之翼」正式登場，完成活動任務即可獲得帥氣的活動限定王子。\n\n\n\n&nbsp;\n\n\n\n\n\n&nbsp;\n\n【以下內容為廠商提供資料原文】\n\n&nbsp;\n\n《夢 100》...."
          },
          "link": {
            "_cdata": "https://gnn.gamer.com.tw/detail.php?sn=288181"
          },
          "pubDate": {
            "_text": "Wed, 02 Jul 2025 16:27:14 +0800"
          }
        },
        {
          "title": {
            "_cdata": "《風之國度》x 三麗鷗《美樂蒂與酷洛米》聯動正式展開 重現羈絆任務與趣味小遊戲"
          },
          "description": {
            "_cdata": "\n\n\n　　傳奇網路旗下手機遊戲《風之國度》今日宣布，三麗鷗《美樂蒂與酷洛米》再度蒞臨《風之國度》。本次聯動不僅經典重現羈絆任務與趣味小遊戲，更全新打造了一整套限定聯動外觀。今年適逢美樂蒂 50 周年與酷洛米 20 周年，當然也少不了周年限定道具在遊戲中登場。\n\n\n\n&nbsp;\n\n\n\n\n聯動正式開始\n\n\n\n&nbsp;...."
          },
          "link": {
            "_cdata": "https://gnn.gamer.com.tw/detail.php?sn=288179"
          },
          "pubDate": {
            "_text": "Wed, 02 Jul 2025 16:24:14 +0800"
          }
        },
        {
          "title": {
            "_cdata": "《神州 Ｍ》迎來首波改版 全新資料片「蒼狼劫」來襲 全新系統「星盤」登場"
          },
          "description": {
            "_cdata": "\n\n\n　　由宇峻奧汀開發製作的原創 MMORPG 正統續作《神州 M》於今（2）日宣布迎來首次大改版 &mdash;「星盤啟命 刑天破界」，全新資料片「蒼狼劫」登場，並推出全新「星盤」系統與七大活動。官方表示，異界禁地的世界王「蒼狼族大汗」也即將現身，為江湖掀起一陣腥風血雨，唯有無畏的俠者方能守護神州大陸。\n\n\n\n\n\n...."
          },
          "link": {
            "_cdata": "https://gnn.gamer.com.tw/detail.php?sn=288178"
          },
          "pubDate": {
            "_text": "Wed, 02 Jul 2025 16:19:35 +0800"
          }
        }
      ]
    }
  }
}