{
  "_declaration": {
    "_attributes": {
      "version": "1.0",
      "encoding": "utf-8"
    }
  },
  "rss": {
    "_attributes": {
      "version": "2.0"
    },
    "channel": {
      "title": {
        "_text": "巴哈姆特 GNN 新聞網"
      },
      "link": {
        "_text": "https://gnn.gamer.com.tw/"
      },
      "description": {
        "_text": "巴哈姆特 GNN 新聞網"
      },
      "language": {
        "_text": "zh-tw"
      },
      "lastBuildDate": {
        "_text": "Tue, 26 Aug 2025 08:39:38 +0800"
      },
      "image": {
        "title": {
          "_text": "巴哈姆特 GNN 新聞網"
        },
        "width": {
          "_text": "154"
        },
        "height": {
          "_text": "99"
        },
        "link": {
          "_text": "https://www.gamer.com.tw/"
        },
        "url": {
          "_text": "https://i2.bahamut.com.tw/bahamut.gif"
        }
      },
      "item": [
        {
          "title": {
            "_cdata": "【試玩】《牧場物語 來吧！風之繁華市集》全語音戀愛與市集經營的全新牧場生活"
          },
          "description": {
            "_cdata": "\n\n　　對於喜愛模擬經營遊戲的玩家來說，《牧場物語》一直是能夠輕鬆紓壓的代表作。最新作品《牧場物語 來吧！風之繁華市集》即將於 8 月 28 日正式在 Nintendo Switch / Nintendo Switch 2 與 Steam 平台推出，本作一方面延續了系列溫馨可愛的美術風格與牧場經營的核心魅力，另一方面也...."
          },
          "link": {
            "_cdata": "https://gnn.gamer.com.tw/detail.php?sn=291185"
          },
          "pubDate": {
            "_text": "Tue, 26 Aug 2025 08:00:01 +0800"
          }
        },
        {
          "title": {
            "_cdata": "《從前從前有個塊魂》公布片頭曲「Katamari Time!」MV"
          },
          "description": {
            "_cdata": "\n\n\n　　萬代南夢宮娛樂旗下預定於 10 月 23 日發售的《從前從前有個塊魂》正式對外公布了本作遊戲開頭影片「Katamari Time!」MV。\n\n&nbsp;\n\n\n\n\n\n\n\n&nbsp;\n\n\n\n\n\n&nbsp;\n\n\n　　繽紛又怪奇的《塊魂》系列睽違 14 年迎來最新作《從前從前有個塊魂》。本次宇宙大王再度不小心撞...."
          },
          "link": {
            "_cdata": "https://gnn.gamer.com.tw/detail.php?sn=291184"
          },
          "pubDate": {
            "_text": "Mon, 25 Aug 2025 23:54:22 +0800"
          }
        },
        {
          "title": {
            "_cdata": "蠟筆小新《我與博士的暑假》《煤炭鎮的小白》2 合 1 套裝 11 月 27 日限量發售"
          },
          "description": {
            "_cdata": "\n\n　　代理商傑仕登宣布，由 Neos 發行的《蠟筆小新》遊戲系列作 ── Nintendo Switch 蠟筆小新《我與博士的暑假》和《煤炭鎮的小白》將於 2025 年 11 月 27 日推出 2 合 1 套裝版本限量發售。\n\n&nbsp;\n\n\n\n\n\n\n\n&nbsp;\n\n\n【以下內容為廠商提供資料原文】\n\n\n&nbs...."
          },
          "link": {
            "_cdata": "https://gnn.gamer.com.tw/detail.php?sn=291183"
          },
          "pubDate": {
            "_text": "Mon, 25 Aug 2025 23:39:57 +0800"
          }
        },
        {
          "title": {
            "_cdata": "《牧場物語 來吧！風之繁華市集》週四發售 寵物及採集系統帶來更多生活樂趣"
          },
          "description": {
            "_cdata": "\n\n　　Marvelous Inc. 今日公開了溫馨生活遊戲《牧場物語》系列最新作品《牧場物語 來吧！風之繁華市集》最新情報特集。在發售前夕，除了重溫本作的重點特色，也同步公開寵物及採集系統等相關介紹，帶領玩家展開微風鎮的新生活！\n\n&nbsp;\n\n\n\n\n\n\n\n&nbsp;\n\n　　《牧場物語 來吧！風之繁華市集》將在 ...."
          },
          "link": {
            "_cdata": "https://gnn.gamer.com.tw/detail.php?sn=291182"
          },
          "pubDate": {
            "_text": "Mon, 25 Aug 2025 23:28:21 +0800"
          }
        },
        {
          "title": {
            "_cdata": "BANDAI 推出 PS1 / PS2 遊戲包裝迷你吊飾轉蛋 包含《捉猴啦》《到哪都相伴》等經典"
          },
          "description": {
            "_cdata": "\n　　BANDAI 宣布，將於 8 月的第 4 週推出以初代 PlayStation（PS1）與 PlayStation 2（PS2）遊戲包裝為主題的轉蛋「遊戲包裝迷你吊飾（PlayStation）」，每次價格 300 日圓。\n\n&nbsp;\n\n\n\n\n\n\n\n&nbsp;\n\n　　該系列轉蛋將收錄以 PS1 與 PS2 遊...."
          },
          "link": {
            "_cdata": "https://gnn.gamer.com.tw/detail.php?sn=291181"
          },
          "pubDate": {
            "_text": "Mon, 25 Aug 2025 19:29:03 +0800"
          }
        },
        {
          "title": {
            "_cdata": "【TGS 25】山田電機宣布與群馬縣共同參展 TGS 帶來電競賽事回顧與社群遊戲平台介紹"
          },
          "description": {
            "_cdata": "\n　　總部位於群馬縣的日本最大規模連鎖家庭電器零售商山田電機宣布，將與群馬縣共同參與預定於 9 月 25～28 日（四～日）在幕張展覽館舉辦之「東京電玩展 2025（Tokyo Game Show 2025）」。\n\n&nbsp;\n\n\n\n\n\n\n\n&nbsp;\n\n　　群馬縣近年來積極透過電子競技推動地方振興，今年將繼續舉辦...."
          },
          "link": {
            "_cdata": "https://gnn.gamer.com.tw/detail.php?sn=291180"
          },
          "pubDate": {
            "_text": "Mon, 25 Aug 2025 19:02:30 +0800"
          }
        },
        {
          "title": {
            "_cdata": "【TGS 25】萬代南夢宮娛樂公布《數碼寶貝物語 時空異客》等展出陣容"
          },
          "description": {
            "_cdata": "\n\n　　萬代南夢宮娛樂宣布，將在 2025 年 9 月 25 日（四）至 9 月 28 日（日）於幕張展覽館舉行的「東京電玩展 2025」（以下簡稱「TGS2025」）設攤展出，於萬代南夢宮娛樂攤位（Hall 6）展示最新的遊戲作品。此外，在「家庭遊戲區」也會設置試玩台，而「ASOBI STORE 快閃店」（Hall ...."
          },
          "link": {
            "_cdata": "https://gnn.gamer.com.tw/detail.php?sn=291179"
          },
          "pubDate": {
            "_text": "Mon, 25 Aug 2025 18:46:05 +0800"
          }
        },
        {
          "title": {
            "_cdata": "靠著萬能水魔法大翻身《雖然除了水魔法之外沒有任何長處，不過只要有現代知識就夠了吧？》第 1 集在台上市"
          },
          "description": {
            "_cdata": "\n\n　　《雖然除了水魔法之外沒有任何長處，不過只要有現代知識就夠了吧？》是由 mono-zo 執筆撰寫，桶乃かもく繪製插畫、並於日本角川出版的輕小說。本次東立出版社推出帶有首刷限定附錄的中文版第 1 集。\n\n&nbsp;\n\n\n\n\n\n\n\n&nbsp;\n\n　　mono-zo 於 2024 年 2 月開始在「成為小說家吧」網...."
          },
          "link": {
            "_cdata": "https://gnn.gamer.com.tw/detail.php?sn=291178"
          },
          "pubDate": {
            "_text": "Mon, 25 Aug 2025 17:59:29 +0800"
          }
        },
        {
          "title": {
            "_cdata": "【TGS 25】KOEI TECMO 確定參展 TGS 將展出《仁王 3》《薩爾達無雙》《忍者外傳 4》等新作試玩"
          },
          "description": {
            "_cdata": "\n　　KOEI TECMO Games 宣布，將參加 9 月 25～28 日（四～日）在幕張展覽館舉行的「東京電玩展 2025」（以下簡稱：TGS2025），並開設「KOEI TECMO Games&nbsp;TGS2025 特別網站」，公開參展作品資訊。\n\n&nbsp;\n\n\n\n\n\n\n\n&nbsp;\n\n　　本次 KOE...."
          },
          "link": {
            "_cdata": "https://gnn.gamer.com.tw/detail.php?sn=291176"
          },
          "pubDate": {
            "_text": "Mon, 25 Aug 2025 17:53:48 +0800"
          }
        },
        {
          "title": {
            "_cdata": "競速模擬遊戲《Project Motor Racing》公開介紹遊戲內容的新宣傳影片"
          },
          "description": {
            "_cdata": "\n\n　　世雅育樂針對將登上 PlayStation 5／Xbox Series X|S／PC（Steam / Epic Games Store / Windows）平台的《Project Motor Racing》公開了全新宣傳影片，並在其中全面展現本作的魅力。\n\n&nbsp;\n\n\n\n\n\n\n\n&nbsp;\n\n\n【以下內...."
          },
          "link": {
            "_cdata": "https://gnn.gamer.com.tw/detail.php?sn=291175"
          },
          "pubDate": {
            "_text": "Mon, 25 Aug 2025 17:52:27 +0800"
          }
        },
        {
          "title": {
            "_cdata": "Bungie 執行長皮特·帕森斯宣布卸任 由《天命 2》總經理與開發長賈斯汀‧杜魯門接任"
          },
          "description": {
            "_cdata": "\n　　索尼互動娛樂（SIE）旗下開發工作室 Bungie 執行長皮特&middot;帕森斯（Pete Parsons）於美國時間 8 月 22 日宣布，將卸下執行長的職務，交棒給《天命 2》總經理與開發長賈斯汀‧杜魯門（Justin Truman）。\n\n&nbsp;\n\n\n\n\n\n皮特&middot;帕森斯（Pete Pa...."
          },
          "link": {
            "_cdata": "https://gnn.gamer.com.tw/detail.php?sn=291174"
          },
          "pubDate": {
            "_text": "Mon, 25 Aug 2025 17:33:09 +0800"
          }
        },
        {
          "title": {
            "_cdata": "戰術 FPS 新作《幽影行動 WRAITH OPS》發布全新預告片 現已於 Steam 開啟首波測試"
          },
          "description": {
            "_cdata": "\n\n　　即將上線的戰術 FPS 新作《幽影行動（WRAITH OPS）》今日發布了最新實機預告片，展示了快節奏的目標導向戰鬥玩法，以及三大職業突擊兵、專家與重裝兵的作戰風采。與此同時，官方宣布首波測試啟動碼已經陸續發放，玩家們可前往 Steam 商店頁點擊加入測試。\n\n&nbsp;\n\n　　官方表示，《幽影行動》專注於打...."
          },
          "link": {
            "_cdata": "https://gnn.gamer.com.tw/detail.php?sn=291173"
          },
          "pubDate": {
            "_text": "Mon, 25 Aug 2025 17:32:49 +0800"
          }
        },
        {
          "title": {
            "_cdata": "短篇動畫《拉拉熊》2026 年 4 月開播 前導視覺圖公開"
          },
          "description": {
            "_cdata": "\n　　於 2024 年 10 月發布將推出新作的《拉拉熊》短篇動畫，正式確定將於 2026 年 4 月開播，官方同時也釋出了前導視覺圖以及主要製作團隊情報。\n\n&nbsp;\n\n\n\n\n\n\n\n&nbsp;\n\n　　《拉拉熊》短篇動畫將由 Production I.G 製作，而先前雖然公布將由《北極百貨的秋乃小姐》導演板津匡覧...."
          },
          "link": {
            "_cdata": "https://gnn.gamer.com.tw/detail.php?sn=291172"
          },
          "pubDate": {
            "_text": "Mon, 25 Aug 2025 17:28:52 +0800"
          }
        },
        {
          "title": {
            "_cdata": "KRAFTON 宣布參與「Esports Nations Cup」國際電競賽事"
          },
          "description": {
            "_cdata": "\n\n　　韓商魁匠團公司 (KRAFTON, INC.) 於今 (25) 日正式宣布，將加入由 Esports World Cup Foundation (EWCF) 主導的全球電競計畫，成為首屆 Esports Nations Cup (ENC) 的官方合作夥伴，與多家全球發行商共同推動此項具有劃時代意義的國際賽事。\n...."
          },
          "link": {
            "_cdata": "https://gnn.gamer.com.tw/detail.php?sn=291171"
          },
          "pubDate": {
            "_text": "Mon, 25 Aug 2025 17:18:31 +0800"
          }
        },
        {
          "title": {
            "_cdata": "《SANDA 變身聖誕老人》釋出動畫正式宣傳影片 關俊彥將參與配音演出"
          },
          "description": {
            "_cdata": "\n\n　　由板垣巴留所著漫畫作品改編，電視動畫《SANDA 變身聖誕老人》今（25）日公開了主視覺圖與正式宣傳影片等作品資訊，並宣布串流將自 10 月 5 日 01:53 起於 Prime Video 世界獨佔配信的消息。\n\n&nbsp;\n\n\n\n\n\n\n\n&nbsp;\n\n　　《SANDA 變身聖誕老人》故事描述，在極端少子...."
          },
          "link": {
            "_cdata": "https://gnn.gamer.com.tw/detail.php?sn=291170"
          },
          "pubDate": {
            "_text": "Mon, 25 Aug 2025 17:14:30 +0800"
          }
        },
        {
          "title": {
            "_cdata": "《星之勇者鬥惡龍》日版宣布 10/31 終止服務 仍預定實施 10 週年活動等更新"
          },
          "description": {
            "_cdata": "\n\n　　SQUARE ENIX 於今（25）日宣布，智慧型手機 RPG《星之勇者鬥惡龍》即將於 2025 年 10 月 31 日（五）結束在日本地區的服務。\n\n&nbsp;\n\n\n\n\n\n\n\n&nbsp;\n\n\n\n　　《星之勇者鬥惡龍》為《勇者鬥惡龍》官方系列手機遊戲，在遊戲中玩家將成為在星球上冒險的勇者，一邊成長一邊對抗迫...."
          },
          "link": {
            "_cdata": "https://gnn.gamer.com.tw/detail.php?sn=291169"
          },
          "pubDate": {
            "_text": "Mon, 25 Aug 2025 16:57:38 +0800"
          }
        },
        {
          "title": {
            "_cdata": "《GTA 線上模式》夏末 GTA 遊戲幣贈送活動舉辦中"
          },
          "description": {
            "_cdata": "\n\n　　Rockstar Games 宣布，現正舉辦《GTA 線上模式》「夏末 GTA 遊戲幣贈送活動」，玩家最多可獲得高達 200 萬 GTA 遊戲幣。此外，西門將在出口載具請求與聯絡人任務支付巨額獎勵、提供免費領取甩尾瓦爾頓 L35 的最後機會，另外還有更多內容。\n\n&nbsp;\n\n\n【以下內容為廠商提供資料原文】...."
          },
          "link": {
            "_cdata": "https://gnn.gamer.com.tw/detail.php?sn=291168"
          },
          "pubDate": {
            "_text": "Mon, 25 Aug 2025 16:46:37 +0800"
          }
        },
        {
          "title": {
            "_cdata": "【TGS 25】CAPCOM 公開 TGS 參展資訊 將展出《惡靈古堡 9：安魂曲》等 8 款作品試玩"
          },
          "description": {
            "_cdata": "\n　　CAPCOM 今日（8/25）公開了預定於 9 月 25～28 日（四～日）在幕張展覽館舉辦之「東京電玩展 2025（Tokyo Game Show 2025）」的首波參展資訊，將提供以《惡靈古堡 9：安魂曲》為首的多款遊戲試玩。\n\n&nbsp;\n\n\n\n\n\n\n\n&nbsp;\n\n現場實體展出\n\n&nbsp;\n\n　　...."
          },
          "link": {
            "_cdata": "https://gnn.gamer.com.tw/detail.php?sn=291167"
          },
          "pubDate": {
            "_text": "Mon, 25 Aug 2025 16:44:21 +0800"
          }
        },
        {
          "title": {
            "_cdata": "《FINAL FANTASY BRAVE EXVIUS》日版問世 10 年後即將終止服務 回憶版 App 確定製作"
          },
          "description": {
            "_cdata": "\n　　SQUARE ENIX 於今（25）日宣布，RPG 手機遊戲《FINAL FANTASY BRAVE EXVIUS》即將於 2025 年 10 月 31 日（五）結束在日本地區的服務。\n\n&nbsp;\n\n\n\n\n\n\n\n&nbsp;\n\n\n　　《FINAL FANTASY BRAVE EXVIUS》主打操作簡易，兼具高...."
          },
          "link": {
            "_cdata": "https://gnn.gamer.com.tw/detail.php?sn=291166"
          },
          "pubDate": {
            "_text": "Mon, 25 Aug 2025 16:26:15 +0800"
          }
        },
        {
          "title": {
            "_cdata": "【書訊】台灣角川 9 月新書《今朝戀心也隨車搖曳》《刀劍神域外傳 推理迷宮 迷宮館殺人事件》"
          },
          "description": {
            "_cdata": "\n\n　　GNN 新聞每月將刊登由各出版社所提供之新書情報，本篇為台灣角川出版社 2025 年 9 月份的注目焦點漫畫、輕小說以及重點預定出版書目一覽。對於其他出版社 9 月份新書情報有興趣之讀者，可注意 GNN 整理各出版社之【書訊】報導：\n\n&nbsp;\n\n\n\n漫畫《今朝戀心也隨車搖曳》（1）\n\n&nbsp;\n\n作者...."
          },
          "link": {
            "_cdata": "https://gnn.gamer.com.tw/detail.php?sn=291165"
          },
          "pubDate": {
            "_text": "Mon, 25 Aug 2025 16:19:42 +0800"
          }
        },
        {
          "title": {
            "_cdata": "必勝客熱血聯名《排球少年！！》推 10 款限量必勝透卡 全台四門市快閃活動登場"
          },
          "description": {
            "_cdata": "\n\n　　必勝客正式宣布與人氣熱血動畫《排球少年！！》展開聯名合作。這波聯名不僅推出獨家主題比薩盒，還有限量發行的《排球少年！！》聯名角色透卡，集結日向翔陽、影山飛雄等多位人氣角色，共打造 10 款隨機透卡，其中更有 2 款隱藏版。不管是購買必勝客的「個人比薩獨享餐」或「一公尺派對盒」都可以加購，且只要單點本次聯名主打的...."
          },
          "link": {
            "_cdata": "https://gnn.gamer.com.tw/detail.php?sn=291164"
          },
          "pubDate": {
            "_text": "Mon, 25 Aug 2025 16:15:06 +0800"
          }
        },
        {
          "title": {
            "_cdata": "《絕區零》x Razer 聯名系列登場 以人氣角色「星見雅」為設計核心推出一系列聯名周邊"
          },
          "description": {
            "_cdata": "\n\n　　全球玩家生活風格領導品牌 Razer 今日宣布攜手 HoYoverse，推出首款《絕區零》官方授權聯名周邊系列 - Razer | 絕區零聯名系列。官方表示，這套兼具收藏價值與電競性能的聯名產品，讓玩家能將新艾利都（New Eridu）的能量帶進全球遊戲戰場。本次聯名以人氣角色星見雅（Hoshimi Miyab...."
          },
          "link": {
            "_cdata": "https://gnn.gamer.com.tw/detail.php?sn=291162"
          },
          "pubDate": {
            "_text": "Mon, 25 Aug 2025 15:48:40 +0800"
          }
        },
        {
          "title": {
            "_cdata": "MediaCreate 8 月 11 日～8 月 17 日一週銷售排行榜 《瑪利歐賽車世界》維持連霸局面"
          },
          "description": {
            "_cdata": "\n　　巴哈姆特 GNN 與日本遊戲業界分析公司 MediaCreate 合作，每週定期刊載由 MediaCreate 調查與統計的日本、台灣與韓國地區家用遊樂器主機遊戲軟體的一週銷售排行榜，供玩家參考。\n\n&nbsp;\n\n\n\n\n\n《瑪利歐賽車世界》\n\n\n\n\n&nbsp;\n\n　　2025 年 8 月 11 日～8 月 1...."
          },
          "link": {
            "_cdata": "https://gnn.gamer.com.tw/detail.php?sn=291161"
          },
          "pubDate": {
            "_text": "Mon, 25 Aug 2025 15:38:13 +0800"
          }
        },
        {
          "title": {
            "_cdata": "《魔靈召喚》舉辦 5 星魔靈免費召喚活動 第 9 季 RTA 鬪王賽開放報名中"
          },
          "description": {
            "_cdata": "\n\n　　韓國遊戲廠商 Com2uS 旗下經典作品《魔靈召喚》推出期間限定活動，為即將開學的莘莘學子送上 5 星魔靈。即日起至 9 月 30 日，累計簽到 1 天即可召喚 5 星魔靈 1 次，累計簽到 7 天可再召喚 1 次，以此類推，總共可召喚 5 次 5 星魔靈，並從中任選 1 隻帶回家。\n\n&nbsp;\n\n\n\n\n\n...."
          },
          "link": {
            "_cdata": "https://gnn.gamer.com.tw/detail.php?sn=291160"
          },
          "pubDate": {
            "_text": "Mon, 25 Aug 2025 15:37:51 +0800"
          }
        },
        {
          "title": {
            "_cdata": "《二重螺旋》公測定檔直播 8/26 登場 將公布全球公測日期與公測版重要情報"
          },
          "description": {
            "_cdata": "\n　　由 HERO GAMES 旗下遊戲工作室 Pan Studio 研運一體打造的雙線幻想 &times; 多維戰鬥二次元遊戲《二重螺旋（Duet Night Abyss）》今（25）日宣布，將於 2025 年 8 月 26 日 19:00（UTC + 8） 舉辦 「公測定檔直播『皎點訪談』」。\n\n\n\n\n\n\n&nbs...."
          },
          "link": {
            "_cdata": "https://gnn.gamer.com.tw/detail.php?sn=291159"
          },
          "pubDate": {
            "_text": "Mon, 25 Aug 2025 15:32:51 +0800"
          }
        },
        {
          "title": {
            "_cdata": "《信長之野望 真戰》CBT 測試定檔 8 月 29 日 預先下載現已開啟"
          },
          "description": {
            "_cdata": "\n\n\n　　由光榮特庫摩《信長之野望・新生》正版授權、《三國志・戰略版》製作團隊打造，青鳥互娛代理的《信長之野望 真戰》今（25）日正式宣布，遊戲即將在 8 月 29 日展開「首次開放測試（CBT 測試）」，並會以限量付費刪檔測試的形式登場，玩家可自即日起透過 Google Play 商店進行預先下載。\n\n\n\n&nbsp...."
          },
          "link": {
            "_cdata": "https://gnn.gamer.com.tw/detail.php?sn=291158"
          },
          "pubDate": {
            "_text": "Mon, 25 Aug 2025 15:28:54 +0800"
          }
        },
        {
          "title": {
            "_cdata": "文化部駐日臺灣文化中心主辦「多元臺灣文化漫畫展」東京開幕"
          },
          "description": {
            "_cdata": "\n\n　　由文化部駐日臺灣文化中心主辦的年度展覽「多元臺灣文化漫畫展」（「-Colorful- ダイバーシティ in 台湾漫画」）於 22 日揭幕。本次參展的臺灣漫畫家阮光民、左萱與重花等 3 位作者，特地來到東京與日本讀者交流。現場更有多位貴賓蒞臨力挺，包括駐日代表處公使周學佑、日本臺灣交流協會理事長谷崎泰明、長年擔任...."
          },
          "link": {
            "_cdata": "https://gnn.gamer.com.tw/detail.php?sn=291157"
          },
          "pubDate": {
            "_text": "Mon, 25 Aug 2025 15:26:10 +0800"
          }
        },
        {
          "title": {
            "_cdata": "輕小說改編 H5 遊戲《異世界悠閒農家 夢想生活》開始事前預約"
          },
          "description": {
            "_cdata": "\n\n　　CTW 宣布，輕小說《異世界悠閒農家》改編遊戲《異世界悠閒農家 夢想生活》開放事前預約。\n\n&nbsp;\n\n\n【以下內容為廠商提供資料原文】\n\n\n&nbsp;\n\n\n\n\n\n\n\n&nbsp;\n\n在異世界，務農。與夥伴共度悠閒時光\n\n&nbsp;\n\n　　以《異世界悠閒農家》世界觀打造的網頁遊戲登場！簡單操作，人人都能...."
          },
          "link": {
            "_cdata": "https://gnn.gamer.com.tw/detail.php?sn=291156"
          },
          "pubDate": {
            "_text": "Mon, 25 Aug 2025 15:16:33 +0800"
          }
        },
        {
          "title": {
            "_cdata": "《LINE 熊大農場》x「小魔女 DOREMI」合作登場 春風 DoReMi 等人氣角色現身"
          },
          "description": {
            "_cdata": "\n\n\n　　農場手遊《LINE 熊大農場》今日宣布與「小魔女 DOREMI」於 8 月 25 日（一）開始進行合作，這次合作中，小魔女 DOREMI 裡的「春風 DoReMi」、「卷機山花」等人氣角色來到熊大農場玩耍，合作期間除了在遊戲內推出各種限定小夥伴與各式各樣的原創裝飾之外，還有列車排名賽等活動，可以在這些活動中獲...."
          },
          "link": {
            "_cdata": "https://gnn.gamer.com.tw/detail.php?sn=291155"
          },
          "pubDate": {
            "_text": "Mon, 25 Aug 2025 14:52:26 +0800"
          }
        },
        {
          "title": {
            "_cdata": "宏碁專為創作者打造 Swift X AI 筆電推出 搭載 AMD Ryzen AI 9 365 與 R5-340 系列處理器"
          },
          "description": {
            "_cdata": "\n\n\n　　宏碁在台推出主打專為專業創作者打造的 Swift X 系列筆電，搭載強大的 NVIDIA GeForce RTX 50 系列筆電 GPU，皆通過 NVIDIA Studio 認證，可透過內建的 NVIDIA Studio 驅動程式增強 AI 生成效能，透過 AI 驅動的光線重建技術，升頻光影效果和解析度，呈現...."
          },
          "link": {
            "_cdata": "https://gnn.gamer.com.tw/detail.php?sn=291154"
          },
          "pubDate": {
            "_text": "Mon, 25 Aug 2025 14:45:46 +0800"
          }
        }
      ]
    }
  }
}